wink_sdk_reference/__init__.py
wink_sdk_reference/api_client.py
wink_sdk_reference/api_response.py
wink_sdk_reference/configuration.py
wink_sdk_reference/exceptions.py
wink_sdk_reference/py.typed
wink_sdk_reference/rest.py
wink_sdk_reference/api/__init__.py
wink_sdk_reference/api/geo_data_api.py
wink_sdk_reference/api/rate_provider_api.py
wink_sdk_reference/api/reference_api.py
wink_sdk_reference/models/__init__.py
wink_sdk_reference/models/count_response_non_authenticated_entity.py
wink_sdk_reference/models/country_lightweight_non_authenticated_entity.py
wink_sdk_reference/models/country_non_authenticated_entity.py
wink_sdk_reference/models/exchange_rate_view_non_authenticated_entity.py
wink_sdk_reference/models/generic_error_message.py
wink_sdk_reference/models/geo_ip_lightweight_non_authenticated_entity.py
wink_sdk_reference/models/geo_ip_non_authenticated_entity.py
wink_sdk_reference/models/geo_json_point_non_authenticated_entity.py
wink_sdk_reference/models/geo_name_country_non_authenticated_entity.py
wink_sdk_reference/models/geo_name_lightweight_non_authenticated_entity.py
wink_sdk_reference/models/geo_name_non_authenticated_entity.py
wink_sdk_reference/models/key_value_pair_administrator.py
wink_sdk_reference/models/key_value_pair_non_authenticated_entity.py
wink_sdk_reference/models/language_non_authenticated_entity.py
wink_sdk_reference/models/page_exchange_rate_view_non_authenticated_entity.py
wink_sdk_reference/models/page_quote_non_authenticated_entity.py
wink_sdk_reference/models/pageable_object_non_authenticated_entity.py
wink_sdk_reference/models/perk_lightweight_non_authenticated_entity.py
wink_sdk_reference/models/quote_lightweight_non_authenticated_entity.py
wink_sdk_reference/models/quote_non_authenticated_entity.py
wink_sdk_reference/models/show_social_networks400_response.py
wink_sdk_reference/models/simple_description_non_authenticated_entity.py
wink_sdk_reference/models/sort_object.py
wink_sdk_reference-0.0.57.dist-info/licenses/LICENSE
wink_sdk_reference-0.0.57.dist-info/METADATA
wink_sdk_reference-0.0.57.dist-info/WHEEL
wink_sdk_reference-0.0.57.dist-info/top_level.txt
wink_sdk_reference-0.0.57.dist-info/RECORD
